galactic_messenger/__init__.py
galactic_messenger/config.py
galactic_messenger/env/env.py
galactic_messenger/src/mail.py
galactic_messenger/src/telegram.py
galactic_messenger/src/utils.py
galactic_messenger/src/whatsapp.py
galactic_messenger/tests/end_to_end/test_mail.py
galactic_messenger/tests/end_to_end/test_telegram.py
galactic_messenger/tests/end_to_end/test_whatsapp.py
galactic_messenger/tests/unit/test_mail.py
galactic_messenger/tests/unit/test_utils.py
galactic_messenger/tests/unit/test_whatsapp.py
galactic_messenger-0.1.6.dist-info/LICENSE
galactic_messenger-0.1.6.dist-info/METADATA
galactic_messenger-0.1.6.dist-info/WHEEL
galactic_messenger-0.1.6.dist-info/top_level.txt
galactic_messenger-0.1.6.dist-info/RECORD
