Metadata-Version: 2.1
Name: galactic-messenger
Version: 0.1.6
Summary: Galactic Messenger is a versatile and efficient Python package designed for sending messages across multiple platforms.
Home-page: https://github.com/Invigilo-AI/Galactic-Messenger
Author: InvigiloAI
Author-email: contact@invigilo.ai
Classifier: Development Status :: 3 - Alpha
Classifier: License :: OSI Approved :: MIT License
Classifier: Programming Language :: Python :: 3
Classifier: Programming Language :: Python :: 3.6
Classifier: Programming Language :: Python :: 3.7
Classifier: Programming Language :: Python :: 3.8
Classifier: Programming Language :: Python :: 3.9
Requires-Python: >=3.9
License-File: LICENSE
Requires-Dist: aiohttp (==3.8.4)
Requires-Dist: aiosignal (==1.3.1)
Requires-Dist: aiosmtplib (==2.0.1)
Requires-Dist: async-timeout (==4.0.2)
Requires-Dist: attrs (==23.1.0)
Requires-Dist: charset-normalizer (==3.1.0)
Requires-Dist: exceptiongroup (==1.1.1)
Requires-Dist: frozenlist (==1.3.3)
Requires-Dist: idna (==3.4)
Requires-Dist: iniconfig (==2.0.0)
Requires-Dist: multidict (==6.0.4)
Requires-Dist: packaging (==23.1)
Requires-Dist: pluggy (==1.0.0)
Requires-Dist: pydantic (==1.10.7)
Requires-Dist: pyrsistent (==0.19.3)
Requires-Dist: pytest (==7.3.1)
Requires-Dist: pytest-asyncio (==0.21.0)
Requires-Dist: python-dotenv (==1.0.0)
Requires-Dist: secure-smtplib (==0.1.1)
Requires-Dist: tomli (==2.0.1)
Requires-Dist: typing-extensions (==4.5.0)
Requires-Dist: yarl (==1.9.2)
